bgesdk/__init__.py
bgesdk/__main__.py
bgesdk/client.py
bgesdk/constants.py
bgesdk/error.py
bgesdk/fs.py
bgesdk/http.py
bgesdk/models.py
bgesdk/utils.py
bgesdk/version.py
bgesdk/management/__init__.py
bgesdk/management/command.py
bgesdk/management/constants.py
bgesdk/management/utils.py
bgesdk/management/validate.py
bgesdk/management/commands/__init__.py
bgesdk/management/commands/config.py
bgesdk/management/commands/login.py
bgesdk/management/commands/model.py
bgesdk/management/commands/model_doc.py
bgesdk/management/commands/token.py
bgesdk/management/commands/workon.py
bgesdk/management/commands/api/__init__.py
bgesdk/management/commands/api/commands/__init__.py
bgesdk/management/commands/api/commands/aggregate_omics_data.py
bgesdk/management/commands/api/commands/applet_url.py
bgesdk/management/commands/api/commands/download.py
bgesdk/management/commands/api/commands/ferry_to_oss.py
bgesdk/management/commands/api/commands/get_data_items.py
bgesdk/management/commands/api/commands/get_externals.py
bgesdk/management/commands/api/commands/get_func_abundance.py
bgesdk/management/commands/api/commands/get_gene_abundance.py
bgesdk/management/commands/api/commands/get_overview.py
bgesdk/management/commands/api/commands/get_range_stream.py
bgesdk/management/commands/api/commands/get_samples.py
bgesdk/management/commands/api/commands/get_taxon_abundance.py
bgesdk/management/commands/api/commands/get_user.py
bgesdk/management/commands/api/commands/get_variants.py
bgesdk/management/commands/api/commands/id_meta.py
bgesdk/management/commands/api/commands/task.py
bgesdk/management/commands/api/commands/upload.py
bgesdk/management/commands/api/commands/upload_dir.py
tests/__init__.py
tests/conftest.py
tests/test_abundance.py
tests/test_fs.py
tests/test_model.py
tests/test_models.py
tests/test_oauth2.py
tests/test_phenotype.py
tests/test_samples.py
tests/test_user.py
tests/test_variants.py
tests/test_wgs.py
bge_python_sdk-1.0.0.dist-info/LICENSE
bge_python_sdk-1.0.0.dist-info/METADATA
bge_python_sdk-1.0.0.dist-info/WHEEL
bge_python_sdk-1.0.0.dist-info/entry_points.txt
bge_python_sdk-1.0.0.dist-info/top_level.txt
bge_python_sdk-1.0.0.dist-info/RECORD
