Metadata-Version: 2.1
Name: bge-python-sdk
Version: 1.0.0
Summary: 可用于调用 BGE 开放平台的相关接口。
Home-page: https://github.com/teambge/bge-python-sdk
Author: leafcoder,xiangji1204
Author-email: leafcoder@gmail.com,xiangji1204@genomics.cn
Maintainer: leafcoder
Maintainer-email: leafcoder@gmail.com
License: MIT
Keywords: bge-python-sdk bge bgesdk sdk
Classifier: Development Status :: 5 - Production/Stable
Classifier: Intended Audience :: Developers
Classifier: License :: OSI Approved :: MIT License
Classifier: Natural Language :: Chinese (Simplified)
Classifier: Operating System :: OS Independent
Classifier: Operating System :: Microsoft :: Windows :: Windows 10
Classifier: Operating System :: POSIX :: Linux
Classifier: Programming Language :: Python
Classifier: Programming Language :: Python :: 3
Classifier: Programming Language :: Python :: 3.6
Classifier: Programming Language :: Python :: 3.7
Classifier: Programming Language :: Python :: 3.8
Classifier: Programming Language :: Python :: 3.9
Classifier: Programming Language :: Python :: 3.10
Classifier: Programming Language :: Python :: 3.11
Classifier: Programming Language :: Python :: 3.12
Classifier: Programming Language :: Python :: 3.13
Classifier: Topic :: Software Development :: Libraries
Classifier: Topic :: Software Development :: Libraries :: Python Modules
Classifier: Topic :: Utilities
Requires-Python: >=3.6.3
License-File: LICENSE
Requires-Dist: aliyun-python-sdk-core
Requires-Dist: six
Requires-Dist: certifi
Requires-Dist: chardet
Requires-Dist: idna
Requires-Dist: requests
Requires-Dist: urllib3
Requires-Dist: oss2
Requires-Dist: docker
Requires-Dist: pimento
Requires-Dist: qprompt
Requires-Dist: requests-toolbelt
Requires-Dist: validator.py
Requires-Dist: python-minifier
Requires-Dist: rich
